{"events":[{"params":[1],"name":"Camera Movement","time":0},{"params":[0],"name":"Camera Movement","time":12800},{"params":[1],"name":"Camera Movement","time":19200},{"params":[0],"name":"Camera Movement","time":25600},{"params":[1],"name":"Camera Movement","time":32000},{"params":["charge",""],"name":"HScript Call","time":37200},{"params":[0,"attack"],"time":38400,"name":"Play Animation"},{"params":[0],"name":"Camera Movement","time":38400},{"params":["blast",""],"time":38400,"name":"HScript Call"},{"params":[1],"name":"Camera Movement","time":44800},{"params":["charge",""],"name":"HScript Call","time":50000},{"params":[0],"name":"Camera Movement","time":51200},{"params":[0,"attack"],"time":51200,"name":"Play Animation"},{"params":["blast",""],"time":51200,"name":"HScript Call"},{"params":[1],"name":"Camera Movement","time":57600},{"params":[0],"name":"Camera Movement","time":64000},{"params":[1],"name":"Camera Movement","time":70400},{"params":["charge",""],"time":75600,"name":"HScript Call"},{"params":[0,"attack"],"time":76800,"name":"Play Animation"},{"params":["blast",""],"time":76800,"name":"HScript Call"},{"params":["charge",""],"name":"HScript Call","time":78800},{"params":["charge",""],"name":"HScript Call","time":78800},{"params":[0],"time":80000,"name":"Camera Movement"},{"params":[0,"attack"],"name":"Play Animation","time":80000},{"params":["blast",""],"name":"HScript Call","time":80000},{"params":[0],"time":80000,"name":"Camera Movement"},{"params":[0,"attack"],"name":"Play Animation","time":80000},{"params":["blast",""],"name":"HScript Call","time":80000},{"params":[0],"name":"Camera Movement","time":83200},{"params":[1],"name":"Camera Movement","time":86400},{"params":[0],"name":"Camera Movement","time":88000},{"params":[1],"name":"Camera Movement","time":96000},{"params":[0],"name":"Camera Movement","time":102400},{"params":[1],"name":"Camera Movement","time":108800},{"params":[0],"name":"Camera Movement","time":131200},{"params":[1],"name":"Camera Movement","time":137600},{"params":[0],"name":"Camera Movement","time":144000},{"params":[1],"name":"Camera Movement","time":150400},{"params":[0],"name":"Camera Movement","time":156800},{"params":[1],"name":"Camera Movement","time":163200},{"params":["charge",""],"time":175200,"name":"HScript Call"},{"params":["blast",""],"time":176000,"name":"HScript Call"},{"params":[0,"attack"],"time":176000,"name":"Play Animation"}],"scrollSpeed":3,"strumLines":[{"strumScale":1,"position":"dad","notes":[{"id":2,"sLen":0,"time":12800,"type":0},{"id":0,"sLen":0,"time":13000,"type":0},{"id":3,"sLen":0,"time":13200,"type":0},{"id":1,"sLen":200,"time":13400,"type":0},{"id":2,"sLen":100,"time":13600,"type":0},{"id":3,"sLen":0,"time":13800,"type":0},{"id":0,"sLen":300,"time":14000,"type":0},{"id":1,"sLen":100,"time":14400,"type":0},{"id":2,"sLen":0,"time":14600,"type":0},{"id":3,"sLen":0,"time":14800,"type":0},{"id":2,"sLen":0,"time":15000,"type":0},{"id":0,"sLen":300,"time":15200,"type":0},{"id":3,"sLen":0,"time":15600,"type":0},{"id":1,"sLen":0,"time":15800,"type":0},{"id":2,"sLen":500,"time":16000,"type":0},{"id":0,"sLen":0,"time":16600,"type":0},{"id":1,"sLen":0,"time":16800,"type":0},{"id":0,"sLen":0,"time":17000,"type":0},{"id":3,"sLen":0,"time":17200,"type":0},{"id":1,"sLen":0,"time":17400,"type":0},{"id":3,"sLen":100,"time":17600,"type":0},{"id":2,"sLen":0,"time":17800,"type":0},{"id":0,"sLen":200,"time":18000,"type":0},{"id":1,"sLen":0,"time":18300,"type":0},{"id":2,"sLen":100,"time":18400,"type":0},{"id":3,"sLen":0,"time":18600,"type":0},{"id":1,"sLen":0,"time":18800,"type":0},{"id":3,"sLen":0,"time":19000,"type":0},{"id":0,"sLen":500,"time":19200,"type":0},{"id":1,"sLen":0,"time":19800,"type":0},{"id":2,"sLen":0,"time":19900,"type":0},{"id":3,"sLen":700,"time":20000,"type":0},{"id":2,"sLen":0,"time":21400,"type":0},{"id":1,"sLen":0,"time":21500,"type":0},{"id":2,"sLen":0,"time":21600,"type":0},{"id":0,"sLen":0,"time":21900,"type":0},{"id":0,"sLen":0,"time":22200,"type":0},{"id":3,"sLen":500,"time":22400,"type":0},{"id":0,"sLen":0,"time":23600,"type":0},{"id":2,"sLen":0,"time":23700,"type":0},{"id":0,"sLen":0,"time":23800,"type":0},{"id":3,"sLen":200,"time":24000,"type":0},{"id":1,"sLen":300,"time":24000,"type":0},{"id":2,"sLen":0,"time":24600,"type":0},{"id":0,"sLen":0,"time":24800,"type":0},{"id":1,"sLen":0,"time":25100,"type":0},{"id":3,"sLen":0,"time":25200,"type":0},{"id":3,"sLen":0,"time":25600,"type":0},{"id":2,"sLen":0,"time":25600,"type":0},{"id":0,"sLen":0,"time":25800,"type":0},{"id":1,"sLen":300,"time":26000,"type":0},{"id":3,"sLen":300,"time":26400,"type":0},{"id":2,"sLen":0,"time":26800,"type":0},{"id":0,"sLen":0,"time":27000,"type":0},{"id":1,"sLen":0,"time":27200,"type":0},{"id":0,"sLen":0,"time":27200,"type":0},{"id":3,"sLen":0,"time":27400,"type":0},{"id":2,"sLen":300,"time":27600,"type":0},{"id":1,"sLen":300,"time":28000,"type":0},{"id":3,"sLen":0,"time":28400,"type":0},{"id":0,"sLen":0,"time":28600,"type":0},{"id":2,"sLen":0,"time":28800,"type":0},{"id":1,"sLen":300,"time":28800,"type":0},{"id":3,"sLen":300,"time":29200,"type":0},{"id":0,"sLen":0,"time":29600,"type":0},{"id":2,"sLen":0,"time":29800,"type":0},{"id":1,"sLen":0,"time":30000,"type":0},{"id":2,"sLen":0,"time":30200,"type":0},{"id":3,"sLen":300,"time":30400,"type":0},{"id":0,"sLen":0,"time":30400,"type":0},{"id":1,"sLen":0,"time":30800,"type":0},{"id":2,"sLen":0,"time":31000,"type":0},{"id":2,"sLen":0,"time":31200,"type":0},{"id":0,"sLen":0,"time":31400,"type":0},{"id":3,"sLen":100,"time":31600,"type":0},{"id":1,"sLen":0,"time":31800,"type":0},{"id":2,"sLen":700,"time":32000,"type":0},{"id":0,"sLen":400,"time":32000,"type":0},{"id":2,"sLen":0,"time":38600,"type":0},{"id":2,"sLen":0,"time":38700,"type":0},{"id":1,"sLen":100,"time":38800,"type":0},{"id":3,"sLen":0,"time":39000,"type":0},{"id":0,"sLen":0,"time":39400,"type":0},{"id":0,"sLen":0,"time":39500,"type":0},{"id":2,"sLen":0,"time":39600,"type":0},{"id":1,"sLen":0,"time":39800,"type":0},{"id":3,"sLen":0,"time":39900,"type":0},{"id":2,"sLen":0,"time":40000,"type":0},{"id":1,"sLen":0,"time":40200,"type":0},{"id":1,"sLen":0,"time":40300,"type":0},{"id":0,"sLen":0,"time":40400,"type":0},{"id":2,"sLen":0,"time":40600,"type":0},{"id":3,"sLen":0,"time":40700,"type":0},{"id":0,"sLen":0,"time":40800,"type":0},{"id":1,"sLen":0,"time":41000,"type":0},{"id":3,"sLen":0,"time":41100,"type":0},{"id":2,"sLen":0,"time":41200,"type":0},{"id":0,"sLen":100,"time":41400,"type":0},{"id":3,"sLen":0,"time":41800,"type":0},{"id":3,"sLen":0,"time":41900,"type":0},{"id":2,"sLen":0,"time":42000,"type":0},{"id":1,"sLen":0,"time":42100,"type":0},{"id":2,"sLen":0,"time":42200,"type":0},{"id":0,"sLen":0,"time":42300,"type":0},{"id":2,"sLen":0,"time":42400,"type":0},{"id":3,"sLen":100,"time":42600,"type":0},{"id":1,"sLen":0,"time":42800,"type":0},{"id":2,"sLen":0,"time":42900,"type":0},{"id":0,"sLen":0,"time":43000,"type":0},{"id":1,"sLen":0,"time":43100,"type":0},{"id":3,"sLen":0,"time":43200,"type":0},{"id":2,"sLen":0,"time":43200,"type":0},{"id":1,"sLen":0,"time":43600,"type":0},{"id":0,"sLen":0,"time":43700,"type":0},{"id":2,"sLen":0,"time":43800,"type":0},{"id":3,"sLen":0,"time":44000,"type":0},{"id":1,"sLen":0,"time":44100,"type":0},{"id":0,"sLen":0,"time":44300,"type":0},{"id":2,"sLen":0,"time":44400,"type":0},{"id":3,"sLen":0,"time":44600,"type":1},{"id":3,"sLen":0,"time":44700,"type":1},{"id":1,"sLen":0,"time":44800,"type":1},{"id":0,"sLen":0,"time":44800,"type":1},{"id":3,"sLen":0,"time":51400,"type":0},{"id":2,"sLen":0,"time":51600,"type":0},{"id":0,"sLen":300,"time":51800,"type":0},{"id":1,"sLen":0,"time":52200,"type":0},{"id":3,"sLen":300,"time":52400,"type":0},{"id":2,"sLen":0,"time":52800,"type":0},{"id":0,"sLen":0,"time":53000,"type":0},{"id":1,"sLen":0,"time":53200,"type":0},{"id":3,"sLen":300,"time":53400,"type":0},{"id":2,"sLen":0,"time":53800,"type":0},{"id":1,"sLen":0,"time":54000,"type":0},{"id":0,"sLen":0,"time":54200,"type":0},{"id":2,"sLen":0,"time":54400,"type":0},{"id":1,"sLen":0,"time":54600,"type":0},{"id":3,"sLen":0,"time":54700,"type":0},{"id":1,"sLen":0,"time":54800,"type":0},{"id":2,"sLen":0,"time":55000,"type":0},{"id":0,"sLen":0,"time":55100,"type":0},{"id":3,"sLen":0,"time":55300,"type":0},{"id":2,"sLen":0,"time":55400,"type":0},{"id":1,"sLen":0,"time":55500,"type":0},{"id":0,"sLen":0,"time":55600,"type":0},{"id":2,"sLen":0,"time":55800,"type":0},{"id":3,"sLen":0,"time":56000,"type":0},{"id":1,"sLen":0,"time":56000,"type":0},{"id":0,"sLen":0,"time":56200,"type":0},{"id":0,"sLen":0,"time":56300,"type":0},{"id":3,"sLen":0,"time":56400,"type":0},{"id":1,"sLen":0,"time":56600,"type":0},{"id":2,"sLen":0,"time":56700,"type":0},{"id":3,"sLen":0,"time":56800,"type":0},{"id":2,"sLen":0,"time":57000,"type":0},{"id":1,"sLen":0,"time":57200,"type":0},{"id":0,"sLen":300,"time":57200,"type":1},{"id":0,"sLen":0,"time":58600,"type":0},{"id":1,"sLen":0,"time":58700,"type":0},{"id":0,"sLen":0,"time":58800,"type":0},{"id":3,"sLen":0,"time":59000,"type":0},{"id":3,"sLen":0,"time":59200,"type":0},{"id":2,"sLen":0,"time":59200,"type":0},{"id":1,"sLen":0,"time":60000,"type":0},{"id":2,"sLen":0,"time":60100,"type":0},{"id":0,"sLen":0,"time":60200,"type":0},{"id":3,"sLen":0,"time":60400,"type":0},{"id":1,"sLen":0,"time":60400,"type":0},{"id":2,"sLen":0,"time":60600,"type":0},{"id":0,"sLen":0,"time":60600,"type":0},{"id":1,"sLen":300,"time":60800,"type":0},{"id":3,"sLen":0,"time":61600,"type":0},{"id":3,"sLen":0,"time":61700,"type":0},{"id":1,"sLen":0,"time":61800,"type":0},{"id":2,"sLen":0,"time":62000,"type":0},{"id":1,"sLen":0,"time":62200,"type":0},{"id":2,"sLen":0,"time":62400,"type":0},{"id":0,"sLen":0,"time":62400,"type":0},{"id":3,"sLen":0,"time":62600,"type":0},{"id":2,"sLen":0,"time":62700,"type":0},{"id":1,"sLen":0,"time":62800,"type":0},{"id":1,"sLen":0,"time":63000,"type":0},{"id":0,"sLen":0,"time":63100,"type":0},{"id":3,"sLen":0,"time":63200,"type":0},{"id":1,"sLen":0,"time":63400,"type":0},{"id":2,"sLen":300,"time":63600,"type":0},{"id":1,"sLen":0,"time":64000,"type":0},{"id":0,"sLen":0,"time":64000,"type":0},{"id":2,"sLen":0,"time":64200,"type":0},{"id":3,"sLen":0,"time":64300,"type":0},{"id":2,"sLen":0,"time":64400,"type":0},{"id":0,"sLen":0,"time":64600,"type":0},{"id":0,"sLen":0,"time":64700,"type":0},{"id":1,"sLen":0,"time":65000,"type":0},{"id":2,"sLen":0,"time":65100,"type":0},{"id":3,"sLen":0,"time":65150,"type":0},{"id":0,"sLen":0,"time":65200,"type":0},{"id":2,"sLen":0,"time":65400,"type":0},{"id":3,"sLen":200,"time":65600,"type":0},{"id":0,"sLen":200,"time":65600,"type":0},{"id":1,"sLen":0,"time":66200,"type":0},{"id":3,"sLen":0,"time":66300,"type":0},{"id":2,"sLen":200,"time":66400,"type":0},{"id":0,"sLen":0,"time":67000,"type":1},{"id":0,"sLen":0,"time":67100,"type":1},{"id":1,"sLen":0,"time":67200,"type":1},{"id":3,"sLen":0,"time":67400,"type":0},{"id":2,"sLen":0,"time":67500,"type":0},{"id":3,"sLen":100,"time":67600,"type":0},{"id":1,"sLen":0,"time":67800,"type":0},{"id":0,"sLen":0,"time":67900,"type":0},{"id":2,"sLen":0,"time":68000,"type":0},{"id":1,"sLen":0,"time":68100,"type":0},{"id":3,"sLen":0,"time":68200,"type":0},{"id":0,"sLen":0,"time":68300,"type":0},{"id":1,"sLen":0,"time":68400,"type":0},{"id":2,"sLen":0,"time":68500,"type":0},{"id":0,"sLen":0,"time":68600,"type":0},{"id":2,"sLen":0,"time":68700,"type":0},{"id":3,"sLen":0,"time":68800,"type":0},{"id":1,"sLen":0,"time":68900,"type":0},{"id":0,"sLen":0,"time":69000,"type":0},{"id":2,"sLen":0,"time":69100,"type":0},{"id":3,"sLen":100,"time":69200,"type":0},{"id":2,"sLen":0,"time":69400,"type":0},{"id":1,"sLen":0,"time":69700,"type":0},{"id":0,"sLen":0,"time":69800,"type":0},{"id":1,"sLen":0,"time":69900,"type":0},{"id":3,"sLen":0,"time":70200,"type":0},{"id":2,"sLen":0,"time":70300,"type":0},{"id":0,"sLen":300,"time":70400,"type":0},{"id":3,"sLen":100,"time":70600,"type":0},{"id":1,"sLen":300,"time":70800,"type":0},{"id":3,"sLen":500,"time":77000,"type":0},{"id":2,"sLen":0,"time":78200,"type":1},{"id":1,"sLen":0,"time":78300,"type":1},{"id":0,"sLen":500,"time":78600,"type":0},{"id":3,"sLen":0,"time":79800,"type":1},{"id":2,"sLen":0,"time":79900,"type":1},{"id":1,"sLen":500,"time":80200,"type":0},{"id":3,"sLen":0,"time":80800,"type":0},{"id":2,"sLen":0,"time":81000,"type":0},{"id":0,"sLen":0,"time":81100,"type":0},{"id":1,"sLen":0,"time":81200,"type":0},{"id":2,"sLen":0,"time":81400,"type":0},{"id":3,"sLen":0,"time":81500,"type":0},{"id":1,"sLen":0,"time":81600,"type":0},{"id":0,"sLen":0,"time":81800,"type":0},{"id":0,"sLen":0,"time":82200,"type":0},{"id":0,"sLen":0,"time":82400,"type":0},{"id":0,"sLen":300,"time":82800,"type":0},{"id":2,"sLen":0,"time":83400,"type":0},{"id":1,"sLen":0,"time":83600,"type":0},{"id":3,"sLen":0,"time":83700,"type":0},{"id":1,"sLen":0,"time":83800,"type":0},{"id":3,"sLen":0,"time":84000,"type":0},{"id":0,"sLen":0,"time":84200,"type":0},{"id":0,"sLen":0,"time":84300,"type":0},{"id":2,"sLen":0,"time":84400,"type":0},{"id":1,"sLen":0,"time":84600,"type":0},{"id":3,"sLen":0,"time":84800,"type":0},{"id":2,"sLen":0,"time":84900,"type":0},{"id":3,"sLen":0,"time":85000,"type":0},{"id":0,"sLen":0,"time":85100,"type":0},{"id":1,"sLen":0,"time":85200,"type":0},{"id":3,"sLen":0,"time":85400,"type":0},{"id":2,"sLen":100,"time":85600,"type":0},{"id":0,"sLen":100,"time":85800,"type":0},{"id":1,"sLen":300,"time":86000,"type":0},{"id":0,"sLen":0,"time":87800,"type":1},{"id":1,"sLen":0,"time":87900,"type":1},{"id":2,"sLen":0,"time":88000,"type":1},{"id":3,"sLen":0,"time":88600,"type":0},{"id":3,"sLen":0,"time":88700,"type":0},{"id":0,"sLen":0,"time":88800,"type":0},{"id":1,"sLen":0,"time":89000,"type":0},{"id":2,"sLen":0,"time":89200,"type":0},{"id":0,"sLen":0,"time":89225,"type":0},{"id":1,"sLen":0,"time":89300,"type":0},{"id":2,"sLen":0,"time":89400,"type":0},{"id":3,"sLen":0,"time":89500,"type":0},{"id":0,"sLen":0,"time":89600,"type":0},{"id":2,"sLen":0,"time":89800,"type":0},{"id":2,"sLen":0,"time":89900,"type":0},{"id":1,"sLen":0,"time":90000,"type":0},{"id":2,"sLen":0,"time":90200,"type":0},{"id":3,"sLen":100,"time":90400,"type":0},{"id":0,"sLen":100,"time":90600,"type":0},{"id":1,"sLen":100,"time":90800,"type":0},{"id":2,"sLen":0,"time":91200,"type":0},{"id":3,"sLen":0,"time":91300,"type":0},{"id":2,"sLen":0,"time":91400,"type":0},{"id":0,"sLen":0,"time":91600,"type":0},{"id":2,"sLen":100,"time":91800,"type":0},{"id":1,"sLen":100,"time":92000,"type":0},{"id":3,"sLen":0,"time":92200,"type":0},{"id":3,"sLen":0,"time":92600,"type":0},{"id":0,"sLen":0,"time":92800,"type":0},{"id":1,"sLen":0,"time":93000,"type":0},{"id":1,"sLen":0,"time":93100,"type":0},{"id":2,"sLen":0,"time":93200,"type":0},{"id":3,"sLen":0,"time":93300,"type":0},{"id":0,"sLen":0,"time":93400,"type":0},{"id":2,"sLen":0,"time":93500,"type":0},{"id":1,"sLen":0,"time":93600,"type":0},{"id":3,"sLen":0,"time":93800,"type":0},{"id":1,"sLen":0,"time":94000,"type":0},{"id":2,"sLen":0,"time":94200,"type":0},{"id":0,"sLen":0,"time":94600,"type":0},{"id":3,"sLen":0,"time":94700,"type":0},{"id":1,"sLen":0,"time":94800,"type":0},{"id":2,"sLen":0,"time":95000,"type":0},{"id":1,"sLen":0,"time":95200,"type":0},{"id":3,"sLen":0,"time":95400,"type":0},{"id":0,"sLen":0,"time":95600,"type":0},{"id":2,"sLen":0,"time":95800,"type":1},{"id":3,"sLen":300,"time":96000,"type":1},{"id":1,"sLen":0,"time":96000,"type":1},{"id":0,"sLen":0,"time":102200,"type":1},{"id":3,"sLen":0,"time":102300,"type":1},{"id":1,"sLen":0,"time":102700,"type":0},{"id":2,"sLen":0,"time":102800,"type":0},{"id":0,"sLen":0,"time":102900,"type":0},{"id":2,"sLen":0,"time":103000,"type":0},{"id":3,"sLen":0,"time":103100,"type":0},{"id":1,"sLen":100,"time":103200,"type":0},{"id":0,"sLen":0,"time":103400,"type":0},{"id":2,"sLen":200,"time":103500,"type":0},{"id":3,"sLen":0,"time":103800,"type":0},{"id":1,"sLen":0,"time":103900,"type":0},{"id":0,"sLen":0,"time":104000,"type":0},{"id":3,"sLen":0,"time":104100,"type":0},{"id":0,"sLen":0,"time":104200,"type":0},{"id":2,"sLen":0,"time":104300,"type":0},{"id":0,"sLen":0,"time":104400,"type":0},{"id":1,"sLen":0,"time":104500,"type":0},{"id":3,"sLen":0,"time":104600,"type":0},{"id":3,"sLen":0,"time":104800,"type":0},{"id":2,"sLen":0,"time":105000,"type":0},{"id":3,"sLen":0,"time":105100,"type":0},{"id":2,"sLen":0,"time":105200,"type":0},{"id":1,"sLen":0,"time":105300,"type":0},{"id":0,"sLen":0,"time":105400,"type":0},{"id":2,"sLen":0,"time":105900,"type":0},{"id":1,"sLen":100,"time":106000,"type":0},{"id":3,"sLen":0,"time":106200,"type":0},{"id":0,"sLen":0,"time":106400,"type":0},{"id":2,"sLen":0,"time":106600,"type":0},{"id":2,"sLen":100,"time":106800,"type":0},{"id":1,"sLen":0,"time":107200,"type":0},{"id":0,"sLen":0,"time":107200,"type":0},{"id":2,"sLen":0,"time":107400,"type":0},{"id":1,"sLen":0,"time":107500,"type":0},{"id":3,"sLen":0,"time":107600,"type":0},{"id":2,"sLen":0,"time":107600,"type":0},{"id":0,"sLen":0,"time":107800,"type":0},{"id":2,"sLen":0,"time":108000,"type":0},{"id":1,"sLen":0,"time":108000,"type":0},{"id":3,"sLen":0,"time":108200,"type":0},{"id":3,"sLen":0,"time":108300,"type":0},{"id":1,"sLen":0,"time":108400,"type":0},{"id":0,"sLen":0,"time":108400,"type":0},{"id":2,"sLen":0,"time":108600,"type":0},{"id":3,"sLen":0,"time":109000,"type":0},{"id":2,"sLen":0,"time":109050,"type":0},{"id":1,"sLen":0,"time":109100,"type":0},{"id":0,"sLen":0,"time":109150,"type":0},{"id":3,"sLen":0,"time":109200,"type":0},{"id":2,"sLen":0,"time":109400,"type":0},{"id":1,"sLen":0,"time":109400,"type":0},{"id":1,"sLen":0,"time":109800,"type":0},{"id":0,"sLen":0,"time":109800,"type":0},{"id":3,"sLen":300,"time":110000,"type":0},{"id":2,"sLen":0,"time":110000,"type":0},{"id":0,"sLen":0,"time":110600,"type":0},{"id":2,"sLen":0,"time":110700,"type":0},{"id":3,"sLen":0,"time":110800,"type":0},{"id":1,"sLen":0,"time":110800,"type":0},{"id":2,"sLen":0,"time":111000,"type":0},{"id":0,"sLen":0,"time":111000,"type":0},{"id":1,"sLen":0,"time":111200,"type":0},{"id":3,"sLen":0,"time":111400,"type":0},{"id":2,"sLen":0,"time":111400,"type":0},{"id":3,"sLen":0,"time":111600,"type":0},{"id":0,"sLen":300,"time":111600,"type":0},{"id":1,"sLen":0,"time":112000,"type":0},{"id":2,"sLen":0,"time":112100,"type":0},{"id":1,"sLen":0,"time":112200,"type":0},{"id":3,"sLen":0,"time":112300,"type":0},{"id":0,"sLen":0,"time":112400,"type":0},{"id":1,"sLen":0,"time":112550,"type":0},{"id":2,"sLen":0,"time":112600,"type":0},{"id":3,"sLen":0,"time":112800,"type":0},{"id":2,"sLen":0,"time":112800,"type":0},{"id":1,"sLen":0,"time":113000,"type":0},{"id":0,"sLen":0,"time":113000,"type":0},{"id":2,"sLen":300,"time":113200,"type":0},{"id":1,"sLen":0,"time":113200,"type":0},{"id":3,"sLen":0,"time":113600,"type":0},{"id":0,"sLen":0,"time":113600,"type":0},{"id":1,"sLen":0,"time":114000,"type":0},{"id":0,"sLen":0,"time":114000,"type":0},{"id":3,"sLen":0,"time":114200,"type":0},{"id":2,"sLen":0,"time":114200,"type":0},{"id":1,"sLen":0,"time":114600,"type":0},{"id":1,"sLen":0,"time":114700,"type":0},{"id":2,"sLen":0,"time":114800,"type":0},{"id":0,"sLen":0,"time":114800,"type":0},{"id":3,"sLen":0,"time":115000,"type":0},{"id":1,"sLen":700,"time":115200,"type":1},{"id":2,"sLen":0,"time":116000,"type":0},{"id":0,"sLen":0,"time":116200,"type":0},{"id":0,"sLen":0,"time":116400,"type":0},{"id":2,"sLen":500,"time":116600,"type":0},{"id":3,"sLen":700,"time":117200,"type":0},{"id":0,"sLen":0,"time":118000,"type":0},{"id":2,"sLen":300,"time":118200,"type":0},{"id":1,"sLen":0,"time":118800,"type":0},{"id":1,"sLen":0,"time":118900,"type":0},{"id":0,"sLen":0,"time":119000,"type":0},{"id":3,"sLen":0,"time":119100,"type":0},{"id":2,"sLen":300,"time":119200,"type":0},{"id":1,"sLen":0,"time":119800,"type":0},{"id":3,"sLen":0,"time":120000,"type":0},{"id":0,"sLen":0,"time":120200,"type":0},{"id":0,"sLen":0,"time":120600,"type":0},{"id":0,"sLen":0,"time":120800,"type":0},{"id":2,"sLen":500,"time":121000,"type":0},{"id":3,"sLen":0,"time":121400,"type":0},{"id":1,"sLen":600,"time":121600,"type":0},{"id":0,"sLen":300,"time":122400,"type":0},{"id":3,"sLen":0,"time":122800,"type":0},{"id":2,"sLen":300,"time":123000,"type":0},{"id":0,"sLen":500,"time":123400,"type":0},{"id":1,"sLen":300,"time":124000,"type":0},{"id":3,"sLen":200,"time":124400,"type":0},{"id":3,"sLen":700,"time":124800,"type":0},{"id":2,"sLen":300,"time":125600,"type":0},{"id":0,"sLen":500,"time":126000,"type":0},{"id":1,"sLen":300,"time":126600,"type":0},{"id":2,"sLen":500,"time":127000,"type":0},{"id":3,"sLen":300,"time":127600,"type":0},{"id":2,"sLen":0,"time":128000,"type":0},{"id":1,"sLen":0,"time":128000,"type":0},{"id":0,"sLen":1100,"time":128000,"type":0},{"id":3,"sLen":0,"time":129600,"type":0},{"id":3,"sLen":0,"time":130000,"type":0},{"id":1,"sLen":0,"time":130400,"type":0},{"id":3,"sLen":0,"time":130500,"type":0},{"id":2,"sLen":0,"time":130600,"type":0},{"id":1,"sLen":0,"time":130700,"type":0},{"id":0,"sLen":0,"time":130800,"type":0},{"id":1,"sLen":0,"time":130850,"type":0},{"id":2,"sLen":0,"time":130900,"type":0},{"id":3,"sLen":0,"time":130950,"type":0},{"id":0,"sLen":0,"time":131000,"type":1},{"id":1,"sLen":0,"time":131050,"type":1},{"id":2,"sLen":0,"time":131100,"type":1},{"id":3,"sLen":0,"time":131150,"type":1},{"id":1,"sLen":0,"time":131200,"type":1},{"id":0,"sLen":0,"time":131200,"type":1},{"id":3,"sLen":0,"time":131400,"type":0},{"id":3,"sLen":0,"time":131500,"type":0},{"id":2,"sLen":0,"time":131600,"type":0},{"id":0,"sLen":0,"time":131800,"type":0},{"id":1,"sLen":0,"time":132200,"type":0},{"id":1,"sLen":0,"time":132300,"type":0},{"id":3,"sLen":100,"time":132400,"type":0},{"id":2,"sLen":0,"time":132600,"type":0},{"id":0,"sLen":0,"time":132700,"type":0},{"id":1,"sLen":100,"time":132800,"type":0},{"id":2,"sLen":0,"time":133000,"type":0},{"id":3,"sLen":0,"time":133100,"type":0},{"id":0,"sLen":100,"time":133200,"type":0},{"id":1,"sLen":0,"time":133400,"type":0},{"id":2,"sLen":0,"time":133500,"type":0},{"id":1,"sLen":0,"time":133600,"type":0},{"id":3,"sLen":0,"time":133800,"type":0},{"id":2,"sLen":0,"time":133900,"type":0},{"id":0,"sLen":0,"time":134000,"type":0},{"id":3,"sLen":100,"time":134200,"type":0},{"id":1,"sLen":0,"time":134600,"type":0},{"id":1,"sLen":0,"time":134700,"type":0},{"id":2,"sLen":0,"time":134800,"type":0},{"id":0,"sLen":0,"time":134900,"type":0},{"id":2,"sLen":0,"time":135000,"type":0},{"id":3,"sLen":0,"time":135100,"type":0},{"id":2,"sLen":0,"time":135200,"type":0},{"id":1,"sLen":100,"time":135400,"type":0},{"id":0,"sLen":0,"time":135600,"type":0},{"id":2,"sLen":0,"time":135700,"type":0},{"id":0,"sLen":0,"time":135800,"type":0},{"id":3,"sLen":0,"time":135900,"type":0},{"id":2,"sLen":0,"time":136000,"type":0},{"id":1,"sLen":0,"time":136000,"type":0},{"id":0,"sLen":0,"time":136400,"type":0},{"id":0,"sLen":0,"time":136500,"type":0},{"id":3,"sLen":0,"time":136600,"type":0},{"id":1,"sLen":0,"time":136800,"type":0},{"id":2,"sLen":0,"time":136900,"type":0},{"id":0,"sLen":0,"time":137100,"type":0},{"id":1,"sLen":0,"time":137200,"type":0},{"id":3,"sLen":0,"time":137400,"type":1},{"id":2,"sLen":0,"time":137500,"type":1},{"id":1,"sLen":0,"time":137600,"type":1},{"id":0,"sLen":0,"time":137600,"type":1},{"id":0,"sLen":0,"time":143800,"type":1},{"id":1,"sLen":0,"time":143900,"type":1},{"id":3,"sLen":0,"time":144000,"type":1},{"id":2,"sLen":0,"time":144000,"type":1},{"id":0,"sLen":0,"time":144200,"type":0},{"id":1,"sLen":0,"time":144300,"type":0},{"id":0,"sLen":0,"time":144400,"type":0},{"id":2,"sLen":0,"time":144500,"type":0},{"id":3,"sLen":0,"time":144600,"type":0},{"id":1,"sLen":0,"time":144800,"type":0},{"id":1,"sLen":0,"time":144900,"type":0},{"id":2,"sLen":100,"time":145000,"type":0},{"id":3,"sLen":0,"time":145200,"type":0},{"id":0,"sLen":100,"time":145200,"type":0},{"id":2,"sLen":0,"time":145600,"type":0},{"id":2,"sLen":0,"time":145700,"type":0},{"id":1,"sLen":0,"time":145800,"type":0},{"id":3,"sLen":0,"time":146000,"type":0},{"id":0,"sLen":0,"time":146200,"type":0},{"id":2,"sLen":0,"time":146300,"type":0},{"id":1,"sLen":0,"time":146400,"type":0},{"id":3,"sLen":0,"time":146500,"type":0},{"id":2,"sLen":100,"time":146600,"type":0},{"id":0,"sLen":200,"time":146800,"type":0},{"id":3,"sLen":0,"time":147200,"type":0},{"id":1,"sLen":0,"time":147300,"type":0},{"id":3,"sLen":0,"time":147400,"type":0},{"id":2,"sLen":0,"time":147500,"type":0},{"id":0,"sLen":0,"time":147600,"type":0},{"id":1,"sLen":0,"time":147800,"type":0},{"id":3,"sLen":0,"time":148000,"type":0},{"id":2,"sLen":0,"time":148100,"type":0},{"id":1,"sLen":0,"time":148200,"type":0},{"id":3,"sLen":0,"time":148400,"type":0},{"id":0,"sLen":0,"time":148400,"type":0},{"id":1,"sLen":0,"time":148600,"type":0},{"id":2,"sLen":0,"time":148700,"type":0},{"id":3,"sLen":0,"time":148800,"type":0},{"id":0,"sLen":0,"time":149000,"type":0},{"id":2,"sLen":0,"time":149200,"type":0},{"id":0,"sLen":0,"time":149400,"type":0},{"id":1,"sLen":0,"time":149600,"type":0},{"id":1,"sLen":0,"time":149700,"type":0},{"id":3,"sLen":100,"time":149800,"type":0},{"id":2,"sLen":0,"time":150000,"type":0},{"id":0,"sLen":0,"time":150200,"type":1},{"id":3,"sLen":0,"time":150600,"type":0},{"id":2,"sLen":0,"time":150650,"type":0},{"id":1,"sLen":0,"time":150700,"type":0},{"id":0,"sLen":0,"time":150750,"type":0},{"id":3,"sLen":0,"time":151000,"type":0},{"id":2,"sLen":0,"time":151000,"type":0},{"id":2,"sLen":0,"time":151400,"type":0},{"id":0,"sLen":0,"time":151400,"type":0},{"id":3,"sLen":0,"time":151600,"type":0},{"id":1,"sLen":0,"time":151600,"type":0},{"id":2,"sLen":0,"time":152200,"type":0},{"id":1,"sLen":0,"time":152300,"type":0},{"id":3,"sLen":0,"time":152400,"type":0},{"id":0,"sLen":0,"time":152400,"type":0},{"id":1,"sLen":0,"time":152600,"type":0},{"id":3,"sLen":0,"time":152800,"type":0},{"id":2,"sLen":0,"time":152800,"type":0},{"id":0,"sLen":0,"time":153000,"type":0},{"id":2,"sLen":200,"time":153200,"type":0},{"id":1,"sLen":0,"time":153200,"type":0},{"id":0,"sLen":0,"time":153600,"type":0},{"id":1,"sLen":0,"time":153700,"type":0},{"id":0,"sLen":0,"time":153800,"type":0},{"id":3,"sLen":0,"time":153900,"type":0},{"id":2,"sLen":0,"time":154000,"type":0},{"id":1,"sLen":0,"time":154000,"type":0},{"id":0,"sLen":0,"time":154150,"type":0},{"id":2,"sLen":0,"time":154200,"type":0},{"id":3,"sLen":0,"time":154400,"type":0},{"id":1,"sLen":0,"time":154600,"type":0},{"id":0,"sLen":0,"time":154600,"type":0},{"id":2,"sLen":300,"time":154800,"type":0},{"id":0,"sLen":0,"time":154800,"type":0},{"id":3,"sLen":0,"time":155200,"type":0},{"id":1,"sLen":0,"time":155200,"type":0},{"id":0,"sLen":0,"time":156500,"type":0},{"id":1,"sLen":0,"time":156600,"type":1},{"id":2,"sLen":0,"time":156700,"type":1},{"id":3,"sLen":0,"time":156800,"type":1},{"id":0,"sLen":0,"time":156800,"type":1},{"id":1,"sLen":0,"time":157000,"type":0},{"id":2,"sLen":0,"time":157200,"type":0},{"id":3,"sLen":300,"time":157400,"type":0},{"id":0,"sLen":0,"time":157600,"type":0},{"id":1,"sLen":0,"time":157800,"type":0},{"id":2,"sLen":300,"time":158000,"type":0},{"id":0,"sLen":0,"time":158000,"type":0},{"id":3,"sLen":100,"time":158400,"type":0},{"id":1,"sLen":100,"time":158600,"type":0},{"id":0,"sLen":0,"time":158800,"type":0},{"id":2,"sLen":0,"time":159000,"type":0},{"id":1,"sLen":0,"time":159100,"type":0},{"id":3,"sLen":300,"time":159200,"type":0},{"id":0,"sLen":100,"time":159600,"type":0},{"id":2,"sLen":0,"time":159800,"type":0},{"id":1,"sLen":500,"time":160000,"type":0},{"id":2,"sLen":0,"time":160600,"type":0},{"id":3,"sLen":100,"time":160800,"type":0},{"id":2,"sLen":0,"time":161000,"type":0},{"id":1,"sLen":0,"time":161200,"type":0},{"id":0,"sLen":0,"time":161400,"type":0},{"id":1,"sLen":0,"time":161600,"type":0},{"id":3,"sLen":0,"time":161800,"type":0},{"id":1,"sLen":0,"time":162000,"type":0},{"id":2,"sLen":0,"time":162200,"type":0},{"id":0,"sLen":300,"time":162400,"type":0},{"id":3,"sLen":0,"time":162800,"type":0},{"id":1,"sLen":0,"time":163000,"type":0},{"id":3,"sLen":500,"time":163200,"type":0},{"id":2,"sLen":0,"time":163800,"type":0},{"id":1,"sLen":0,"time":163900,"type":0},{"id":0,"sLen":700,"time":164000,"type":0},{"id":1,"sLen":0,"time":165400,"type":0},{"id":2,"sLen":0,"time":165500,"type":0},{"id":1,"sLen":0,"time":165600,"type":0},{"id":3,"sLen":0,"time":165900,"type":0},{"id":0,"sLen":0,"time":166200,"type":0},{"id":2,"sLen":500,"time":166400,"type":0},{"id":0,"sLen":0,"time":167600,"type":0},{"id":1,"sLen":0,"time":167700,"type":0},{"id":0,"sLen":0,"time":167800,"type":0},{"id":3,"sLen":500,"time":168000,"type":0},{"id":2,"sLen":0,"time":168000,"type":0},{"id":1,"sLen":0,"time":168600,"type":0},{"id":2,"sLen":0,"time":168800,"type":0},{"id":0,"sLen":0,"time":168800,"type":0},{"id":3,"sLen":0,"time":169150,"type":0},{"id":1,"sLen":300,"time":169200,"type":0},{"id":2,"sLen":1200,"time":169600,"type":0},{"id":0,"sLen":1200,"time":169600,"type":0}],"characters":["Turmoil"],"type":0,"visible":true,"strumPos":[96,50]},{"strumScale":1,"position":"boyfriend","notes":[{"id":2,"sLen":0,"time":19200,"type":0},{"id":0,"sLen":0,"time":19400,"type":0},{"id":3,"sLen":0,"time":19600,"type":0},{"id":1,"sLen":200,"time":19800,"type":0},{"id":2,"sLen":100,"time":20000,"type":0},{"id":3,"sLen":0,"time":20200,"type":0},{"id":0,"sLen":300,"time":20400,"type":0},{"id":1,"sLen":100,"time":20800,"type":0},{"id":2,"sLen":0,"time":21000,"type":0},{"id":3,"sLen":0,"time":21200,"type":0},{"id":2,"sLen":0,"time":21400,"type":0},{"id":0,"sLen":300,"time":21600,"type":0},{"id":3,"sLen":100,"time":22000,"type":0},{"id":1,"sLen":100,"time":22200,"type":0},{"id":2,"sLen":500,"time":22400,"type":0},{"id":0,"sLen":0,"time":23000,"type":0},{"id":1,"sLen":0,"time":23200,"type":0},{"id":0,"sLen":0,"time":23400,"type":0},{"id":3,"sLen":0,"time":23600,"type":0},{"id":1,"sLen":0,"time":23800,"type":0},{"id":3,"sLen":100,"time":24000,"type":0},{"id":2,"sLen":0,"time":24200,"type":0},{"id":0,"sLen":0,"time":24400,"type":0},{"id":1,"sLen":0,"time":24700,"type":0},{"id":2,"sLen":100,"time":24800,"type":0},{"id":3,"sLen":0,"time":25000,"type":0},{"id":1,"sLen":0,"time":25200,"type":0},{"id":3,"sLen":0,"time":25400,"type":0},{"id":0,"sLen":400,"time":25600,"type":0},{"id":3,"sLen":0,"time":32000,"type":0},{"id":2,"sLen":0,"time":32000,"type":0},{"id":0,"sLen":0,"time":32200,"type":0},{"id":1,"sLen":300,"time":32400,"type":0},{"id":3,"sLen":300,"time":32800,"type":0},{"id":2,"sLen":0,"time":33200,"type":0},{"id":0,"sLen":0,"time":33400,"type":0},{"id":1,"sLen":0,"time":33600,"type":0},{"id":0,"sLen":0,"time":33600,"type":0},{"id":3,"sLen":0,"time":33800,"type":0},{"id":2,"sLen":300,"time":34000,"type":0},{"id":1,"sLen":300,"time":34400,"type":0},{"id":3,"sLen":0,"time":34800,"type":0},{"id":0,"sLen":0,"time":35000,"type":0},{"id":2,"sLen":0,"time":35200,"type":0},{"id":1,"sLen":300,"time":35200,"type":0},{"id":3,"sLen":300,"time":35600,"type":0},{"id":0,"sLen":0,"time":36000,"type":0},{"id":2,"sLen":0,"time":36200,"type":0},{"id":1,"sLen":0,"time":36400,"type":0},{"id":2,"sLen":0,"time":36600,"type":0},{"id":3,"sLen":300,"time":36800,"type":0},{"id":0,"sLen":0,"time":36800,"type":0},{"id":1,"sLen":0,"time":37200,"type":0},{"id":2,"sLen":0,"time":37400,"type":0},{"id":2,"sLen":0,"time":37600,"type":0},{"id":0,"sLen":0,"time":37800,"type":0},{"id":3,"sLen":300,"time":38000,"type":0},{"id":1,"sLen":100,"time":38200,"type":0},{"id":2,"sLen":700,"time":38400,"type":1},{"id":0,"sLen":0,"time":44800,"type":1},{"id":2,"sLen":0,"time":45000,"type":0},{"id":2,"sLen":0,"time":45100,"type":0},{"id":1,"sLen":100,"time":45200,"type":0},{"id":3,"sLen":100,"time":45400,"type":0},{"id":0,"sLen":0,"time":45800,"type":0},{"id":0,"sLen":0,"time":45900,"type":0},{"id":2,"sLen":0,"time":46000,"type":0},{"id":1,"sLen":0,"time":46200,"type":0},{"id":3,"sLen":0,"time":46300,"type":0},{"id":2,"sLen":0,"time":46400,"type":0},{"id":1,"sLen":0,"time":46600,"type":0},{"id":1,"sLen":0,"time":46700,"type":0},{"id":0,"sLen":0,"time":46800,"type":0},{"id":2,"sLen":0,"time":47000,"type":0},{"id":3,"sLen":0,"time":47100,"type":0},{"id":0,"sLen":0,"time":47200,"type":0},{"id":1,"sLen":0,"time":47400,"type":0},{"id":3,"sLen":0,"time":47500,"type":0},{"id":2,"sLen":0,"time":47600,"type":0},{"id":0,"sLen":100,"time":47800,"type":0},{"id":3,"sLen":0,"time":48200,"type":0},{"id":3,"sLen":0,"time":48300,"type":0},{"id":2,"sLen":0,"time":48400,"type":0},{"id":1,"sLen":0,"time":48500,"type":0},{"id":2,"sLen":0,"time":48600,"type":0},{"id":0,"sLen":0,"time":48700,"type":0},{"id":2,"sLen":0,"time":48800,"type":0},{"id":3,"sLen":100,"time":49000,"type":0},{"id":1,"sLen":0,"time":49200,"type":0},{"id":2,"sLen":0,"time":49300,"type":0},{"id":0,"sLen":0,"time":49400,"type":0},{"id":1,"sLen":0,"time":49500,"type":0},{"id":3,"sLen":0,"time":49600,"type":0},{"id":2,"sLen":0,"time":49600,"type":0},{"id":1,"sLen":0,"time":50000,"type":0},{"id":0,"sLen":0,"time":50100,"type":0},{"id":2,"sLen":0,"time":50200,"type":0},{"id":3,"sLen":0,"time":50400,"type":0},{"id":1,"sLen":0,"time":50500,"type":0},{"id":0,"sLen":0,"time":50700,"type":0},{"id":2,"sLen":0,"time":50800,"type":0},{"id":3,"sLen":0,"time":51000,"type":0},{"id":1,"sLen":0,"time":51000,"type":0},{"id":2,"sLen":0,"time":51200,"type":1},{"id":0,"sLen":0,"time":51200,"type":1},{"id":1,"sLen":0,"time":57600,"type":1},{"id":3,"sLen":0,"time":57800,"type":0},{"id":2,"sLen":0,"time":58000,"type":0},{"id":0,"sLen":300,"time":58200,"type":0},{"id":1,"sLen":0,"time":58600,"type":0},{"id":3,"sLen":300,"time":58800,"type":0},{"id":2,"sLen":0,"time":59200,"type":0},{"id":0,"sLen":0,"time":59400,"type":0},{"id":1,"sLen":0,"time":59600,"type":0},{"id":3,"sLen":300,"time":59800,"type":0},{"id":2,"sLen":0,"time":60200,"type":0},{"id":1,"sLen":0,"time":60400,"type":0},{"id":0,"sLen":0,"time":60600,"type":0},{"id":2,"sLen":0,"time":60800,"type":0},{"id":1,"sLen":0,"time":61000,"type":0},{"id":3,"sLen":0,"time":61100,"type":0},{"id":1,"sLen":0,"time":61200,"type":0},{"id":2,"sLen":0,"time":61400,"type":0},{"id":0,"sLen":0,"time":61500,"type":0},{"id":1,"sLen":0,"time":61600,"type":0},{"id":3,"sLen":0,"time":61700,"type":0},{"id":2,"sLen":0,"time":61800,"type":0},{"id":1,"sLen":0,"time":61900,"type":0},{"id":0,"sLen":0,"time":62000,"type":0},{"id":2,"sLen":0,"time":62200,"type":0},{"id":1,"sLen":0,"time":62400,"type":0},{"id":3,"sLen":0,"time":62400,"type":0},{"id":0,"sLen":0,"time":62600,"type":0},{"id":0,"sLen":0,"time":62700,"type":0},{"id":3,"sLen":0,"time":62800,"type":0},{"id":1,"sLen":0,"time":63000,"type":0},{"id":2,"sLen":0,"time":63100,"type":0},{"id":3,"sLen":0,"time":63200,"type":0},{"id":2,"sLen":0,"time":63400,"type":0},{"id":0,"sLen":300,"time":63600,"type":0},{"id":3,"sLen":100,"time":63800,"type":0},{"id":1,"sLen":0,"time":64000,"type":0},{"id":2,"sLen":0,"time":64000,"type":0},{"id":2,"sLen":300,"time":70000,"type":0},{"id":1,"sLen":0,"time":70400,"type":0},{"id":0,"sLen":0,"time":70400,"type":0},{"id":2,"sLen":0,"time":70600,"type":0},{"id":3,"sLen":0,"time":70700,"type":0},{"id":2,"sLen":0,"time":70800,"type":0},{"id":0,"sLen":0,"time":71000,"type":0},{"id":0,"sLen":0,"time":71100,"type":0},{"id":1,"sLen":0,"time":71300,"type":0},{"id":3,"sLen":0,"time":71500,"type":0},{"id":2,"sLen":0,"time":71600,"type":0},{"id":1,"sLen":0,"time":71800,"type":0},{"id":3,"sLen":200,"time":72000,"type":0},{"id":0,"sLen":200,"time":72000,"type":0},{"id":1,"sLen":0,"time":72600,"type":0},{"id":3,"sLen":0,"time":72700,"type":0},{"id":2,"sLen":200,"time":72800,"type":0},{"id":0,"sLen":0,"time":73400,"type":0},{"id":0,"sLen":0,"time":73500,"type":0},{"id":1,"sLen":0,"time":73600,"type":0},{"id":3,"sLen":0,"time":73800,"type":0},{"id":2,"sLen":0,"time":73850,"type":0},{"id":1,"sLen":0,"time":73900,"type":0},{"id":0,"sLen":0,"time":73950,"type":0},{"id":3,"sLen":0,"time":74000,"type":0},{"id":1,"sLen":0,"time":74200,"type":0},{"id":0,"sLen":0,"time":74300,"type":0},{"id":2,"sLen":0,"time":74400,"type":0},{"id":1,"sLen":0,"time":74500,"type":0},{"id":3,"sLen":0,"time":74600,"type":0},{"id":0,"sLen":0,"time":74700,"type":0},{"id":1,"sLen":0,"time":74800,"type":0},{"id":2,"sLen":0,"time":74900,"type":0},{"id":0,"sLen":0,"time":75000,"type":0},{"id":2,"sLen":0,"time":75100,"type":0},{"id":3,"sLen":0,"time":75200,"type":0},{"id":1,"sLen":0,"time":75300,"type":0},{"id":0,"sLen":0,"time":75400,"type":0},{"id":2,"sLen":0,"time":75500,"type":0},{"id":3,"sLen":0,"time":75600,"type":0},{"id":1,"sLen":0,"time":75800,"type":0},{"id":1,"sLen":0,"time":76100,"type":0},{"id":0,"sLen":0,"time":76200,"type":0},{"id":1,"sLen":0,"time":76300,"type":0},{"id":3,"sLen":0,"time":76400,"type":0},{"id":3,"sLen":0,"time":76600,"type":0},{"id":2,"sLen":0,"time":76700,"type":0},{"id":1,"sLen":0,"time":76800,"type":1},{"id":0,"sLen":700,"time":76800,"type":1},{"id":1,"sLen":0,"time":78200,"type":0},{"id":2,"sLen":0,"time":78300,"type":0},{"id":3,"sLen":700,"time":78400,"type":1},{"id":0,"sLen":0,"time":78400,"type":1},{"id":0,"sLen":0,"time":79800,"type":0},{"id":1,"sLen":0,"time":79900,"type":0},{"id":3,"sLen":0,"time":80000,"type":1},{"id":2,"sLen":700,"time":80000,"type":1},{"id":0,"sLen":0,"time":80800,"type":0},{"id":1,"sLen":0,"time":81000,"type":0},{"id":3,"sLen":0,"time":81100,"type":0},{"id":2,"sLen":0,"time":81200,"type":0},{"id":1,"sLen":0,"time":81400,"type":0},{"id":0,"sLen":0,"time":81500,"type":0},{"id":2,"sLen":0,"time":81600,"type":0},{"id":3,"sLen":1300,"time":81800,"type":0},{"id":2,"sLen":0,"time":86600,"type":0},{"id":1,"sLen":0,"time":86800,"type":0},{"id":3,"sLen":0,"time":86900,"type":0},{"id":1,"sLen":0,"time":87000,"type":0},{"id":3,"sLen":0,"time":87200,"type":0},{"id":0,"sLen":0,"time":87400,"type":0},{"id":0,"sLen":0,"time":87500,"type":0},{"id":2,"sLen":0,"time":87600,"type":0},{"id":3,"sLen":0,"time":87800,"type":0},{"id":2,"sLen":0,"time":87900,"type":0},{"id":1,"sLen":0,"time":88000,"type":1},{"id":1,"sLen":0,"time":89200,"type":0},{"id":0,"sLen":0,"time":89300,"type":0},{"id":3,"sLen":0,"time":89400,"type":0},{"id":2,"sLen":0,"time":89500,"type":0},{"id":1,"sLen":0,"time":89600,"type":0},{"id":0,"sLen":0,"time":96000,"type":1},{"id":2,"sLen":0,"time":96200,"type":0},{"id":2,"sLen":0,"time":96300,"type":0},{"id":1,"sLen":0,"time":96400,"type":0},{"id":2,"sLen":0,"time":96600,"type":0},{"id":3,"sLen":100,"time":96800,"type":0},{"id":0,"sLen":100,"time":97000,"type":0},{"id":1,"sLen":300,"time":97200,"type":0},{"id":2,"sLen":0,"time":97600,"type":0},{"id":3,"sLen":0,"time":97700,"type":0},{"id":2,"sLen":0,"time":97800,"type":0},{"id":0,"sLen":0,"time":98000,"type":0},{"id":2,"sLen":100,"time":98200,"type":0},{"id":1,"sLen":100,"time":98400,"type":0},{"id":3,"sLen":0,"time":98600,"type":0},{"id":3,"sLen":300,"time":98800,"type":0},{"id":0,"sLen":0,"time":99200,"type":0},{"id":1,"sLen":0,"time":99400,"type":0},{"id":1,"sLen":0,"time":99500,"type":0},{"id":2,"sLen":0,"time":99600,"type":0},{"id":0,"sLen":0,"time":99800,"type":0},{"id":2,"sLen":0,"time":99900,"type":0},{"id":1,"sLen":0,"time":100000,"type":0},{"id":3,"sLen":0,"time":100200,"type":0},{"id":1,"sLen":0,"time":100400,"type":0},{"id":2,"sLen":0,"time":100600,"type":0},{"id":0,"sLen":0,"time":101000,"type":0},{"id":3,"sLen":0,"time":101100,"type":0},{"id":1,"sLen":0,"time":101200,"type":0},{"id":2,"sLen":0,"time":101400,"type":0},{"id":1,"sLen":700,"time":101600,"type":0},{"id":3,"sLen":0,"time":101800,"type":0},{"id":0,"sLen":0,"time":102000,"type":0},{"id":2,"sLen":0,"time":102200,"type":0},{"id":3,"sLen":0,"time":102600,"type":0},{"id":2,"sLen":0,"time":102650,"type":0},{"id":1,"sLen":0,"time":102700,"type":0},{"id":0,"sLen":0,"time":102750,"type":0},{"id":3,"sLen":0,"time":102800,"type":0},{"id":2,"sLen":0,"time":103000,"type":0},{"id":1,"sLen":0,"time":103000,"type":0},{"id":0,"sLen":0,"time":103400,"type":0},{"id":1,"sLen":0,"time":103400,"type":0},{"id":3,"sLen":300,"time":103600,"type":0},{"id":2,"sLen":0,"time":103600,"type":0},{"id":0,"sLen":0,"time":104200,"type":0},{"id":2,"sLen":0,"time":104300,"type":0},{"id":3,"sLen":0,"time":104400,"type":0},{"id":1,"sLen":0,"time":104400,"type":0},{"id":2,"sLen":0,"time":104600,"type":0},{"id":0,"sLen":0,"time":104600,"type":0},{"id":1,"sLen":0,"time":104800,"type":0},{"id":3,"sLen":0,"time":105000,"type":0},{"id":2,"sLen":0,"time":105000,"type":0},{"id":3,"sLen":0,"time":105200,"type":0},{"id":0,"sLen":300,"time":105200,"type":0},{"id":1,"sLen":0,"time":105600,"type":0},{"id":2,"sLen":0,"time":105700,"type":0},{"id":1,"sLen":0,"time":105800,"type":0},{"id":3,"sLen":0,"time":105900,"type":0},{"id":0,"sLen":0,"time":106000,"type":0},{"id":1,"sLen":0,"time":106150,"type":0},{"id":2,"sLen":0,"time":106200,"type":0},{"id":2,"sLen":0,"time":106400,"type":0},{"id":3,"sLen":0,"time":106400,"type":0},{"id":0,"sLen":0,"time":106600,"type":0},{"id":1,"sLen":0,"time":106600,"type":0},{"id":2,"sLen":300,"time":106800,"type":0},{"id":1,"sLen":0,"time":106800,"type":0},{"id":3,"sLen":0,"time":107200,"type":0},{"id":0,"sLen":0,"time":107200,"type":0},{"id":0,"sLen":0,"time":107600,"type":0},{"id":1,"sLen":0,"time":107600,"type":0},{"id":3,"sLen":0,"time":107800,"type":0},{"id":2,"sLen":0,"time":107800,"type":0},{"id":1,"sLen":0,"time":108200,"type":0},{"id":1,"sLen":0,"time":108300,"type":0},{"id":2,"sLen":0,"time":108400,"type":0},{"id":0,"sLen":0,"time":108400,"type":0},{"id":3,"sLen":0,"time":108600,"type":0},{"id":1,"sLen":0,"time":108800,"type":0},{"id":1,"sLen":0,"time":109100,"type":0},{"id":2,"sLen":0,"time":109200,"type":0},{"id":0,"sLen":0,"time":109300,"type":0},{"id":2,"sLen":0,"time":109400,"type":0},{"id":3,"sLen":0,"time":109500,"type":0},{"id":1,"sLen":0,"time":109600,"type":0},{"id":2,"sLen":200,"time":109900,"type":0},{"id":3,"sLen":0,"time":110200,"type":0},{"id":1,"sLen":0,"time":110300,"type":0},{"id":0,"sLen":0,"time":110400,"type":0},{"id":3,"sLen":0,"time":110500,"type":0},{"id":0,"sLen":0,"time":110600,"type":0},{"id":2,"sLen":0,"time":110700,"type":0},{"id":0,"sLen":0,"time":110800,"type":0},{"id":1,"sLen":0,"time":110900,"type":0},{"id":3,"sLen":0,"time":111000,"type":0},{"id":2,"sLen":0,"time":111100,"type":0},{"id":3,"sLen":0,"time":111200,"type":0},{"id":0,"sLen":0,"time":111300,"type":0},{"id":2,"sLen":0,"time":111400,"type":0},{"id":0,"sLen":0,"time":111500,"type":0},{"id":1,"sLen":0,"time":111600,"type":0},{"id":3,"sLen":0,"time":111700,"type":0},{"id":2,"sLen":100,"time":111800,"type":0},{"id":2,"sLen":0,"time":112300,"type":0},{"id":0,"sLen":0,"time":112400,"type":0},{"id":1,"sLen":0,"time":112500,"type":0},{"id":3,"sLen":0,"time":112600,"type":0},{"id":2,"sLen":0,"time":112600,"type":0},{"id":0,"sLen":100,"time":112800,"type":0},{"id":2,"sLen":100,"time":113000,"type":0},{"id":3,"sLen":100,"time":113200,"type":0},{"id":0,"sLen":0,"time":113600,"type":0},{"id":1,"sLen":0,"time":113600,"type":0},{"id":2,"sLen":0,"time":113800,"type":0},{"id":1,"sLen":0,"time":113900,"type":0},{"id":3,"sLen":0,"time":114000,"type":0},{"id":2,"sLen":0,"time":114000,"type":0},{"id":0,"sLen":0,"time":114200,"type":0},{"id":2,"sLen":0,"time":114400,"type":0},{"id":1,"sLen":0,"time":114400,"type":0},{"id":3,"sLen":0,"time":114600,"type":0},{"id":3,"sLen":0,"time":114700,"type":0},{"id":1,"sLen":0,"time":114800,"type":0},{"id":0,"sLen":0,"time":114800,"type":0},{"id":2,"sLen":0,"time":115000,"type":0},{"id":3,"sLen":700,"time":115200,"type":1},{"id":1,"sLen":0,"time":115200,"type":1},{"id":0,"sLen":700,"time":115600,"type":0},{"id":2,"sLen":1100,"time":116000,"type":0},{"id":1,"sLen":1100,"time":116800,"type":0},{"id":3,"sLen":300,"time":118000,"type":0},{"id":2,"sLen":700,"time":118400,"type":0},{"id":0,"sLen":300,"time":118800,"type":0},{"id":1,"sLen":300,"time":119200,"type":0},{"id":3,"sLen":300,"time":119600,"type":0},{"id":2,"sLen":700,"time":120000,"type":0},{"id":0,"sLen":700,"time":120400,"type":0},{"id":1,"sLen":700,"time":120800,"type":0},{"id":3,"sLen":300,"time":121200,"type":0},{"id":2,"sLen":1500,"time":121600,"type":0},{"id":1,"sLen":1100,"time":122800,"type":0},{"id":3,"sLen":300,"time":123600,"type":0},{"id":0,"sLen":1400,"time":124000,"type":0},{"id":2,"sLen":900,"time":124800,"type":0},{"id":3,"sLen":1000,"time":126000,"type":0},{"id":0,"sLen":0,"time":126200,"type":0},{"id":1,"sLen":0,"time":126400,"type":0},{"id":2,"sLen":700,"time":126800,"type":0},{"id":1,"sLen":300,"time":127600,"type":0},{"id":0,"sLen":0,"time":128000,"type":0},{"id":2,"sLen":0,"time":128000,"type":0},{"id":3,"sLen":900,"time":128000,"type":0},{"id":1,"sLen":0,"time":129600,"type":0},{"id":1,"sLen":0,"time":130000,"type":0},{"id":1,"sLen":0,"time":130400,"type":0},{"id":3,"sLen":0,"time":130500,"type":0},{"id":2,"sLen":0,"time":130600,"type":0},{"id":1,"sLen":0,"time":130700,"type":0},{"id":0,"sLen":0,"time":130800,"type":0},{"id":1,"sLen":0,"time":130850,"type":0},{"id":2,"sLen":0,"time":130900,"type":0},{"id":3,"sLen":0,"time":130950,"type":0},{"id":0,"sLen":0,"time":131000,"type":0},{"id":1,"sLen":0,"time":131050,"type":0},{"id":2,"sLen":0,"time":131100,"type":0},{"id":3,"sLen":0,"time":131150,"type":0},{"id":1,"sLen":0,"time":137600,"type":1},{"id":0,"sLen":0,"time":137600,"type":1},{"id":3,"sLen":0,"time":137800,"type":0},{"id":3,"sLen":0,"time":137900,"type":0},{"id":2,"sLen":0,"time":138000,"type":0},{"id":0,"sLen":0,"time":138200,"type":0},{"id":1,"sLen":0,"time":138600,"type":0},{"id":1,"sLen":0,"time":138700,"type":0},{"id":3,"sLen":100,"time":138800,"type":0},{"id":2,"sLen":0,"time":139000,"type":0},{"id":0,"sLen":0,"time":139100,"type":0},{"id":1,"sLen":100,"time":139200,"type":0},{"id":2,"sLen":0,"time":139400,"type":0},{"id":3,"sLen":0,"time":139500,"type":0},{"id":0,"sLen":100,"time":139600,"type":0},{"id":1,"sLen":0,"time":139800,"type":0},{"id":2,"sLen":0,"time":139900,"type":0},{"id":1,"sLen":0,"time":140000,"type":0},{"id":3,"sLen":0,"time":140200,"type":0},{"id":2,"sLen":0,"time":140300,"type":0},{"id":0,"sLen":0,"time":140400,"type":0},{"id":3,"sLen":100,"time":140600,"type":0},{"id":1,"sLen":0,"time":141000,"type":0},{"id":1,"sLen":0,"time":141100,"type":0},{"id":2,"sLen":0,"time":141200,"type":0},{"id":0,"sLen":0,"time":141300,"type":0},{"id":2,"sLen":0,"time":141400,"type":0},{"id":3,"sLen":0,"time":141500,"type":0},{"id":2,"sLen":0,"time":141600,"type":0},{"id":1,"sLen":100,"time":141800,"type":0},{"id":0,"sLen":0,"time":142000,"type":0},{"id":2,"sLen":0,"time":142100,"type":0},{"id":0,"sLen":0,"time":142200,"type":0},{"id":1,"sLen":0,"time":142300,"type":0},{"id":3,"sLen":0,"time":142350,"type":0},{"id":2,"sLen":0,"time":142400,"type":0},{"id":0,"sLen":0,"time":142800,"type":0},{"id":0,"sLen":0,"time":142900,"type":0},{"id":3,"sLen":0,"time":143000,"type":0},{"id":1,"sLen":0,"time":143200,"type":0},{"id":2,"sLen":0,"time":143400,"type":0},{"id":0,"sLen":0,"time":143500,"type":0},{"id":1,"sLen":0,"time":143700,"type":0},{"id":3,"sLen":0,"time":143800,"type":0},{"id":3,"sLen":0,"time":144200,"type":0},{"id":2,"sLen":0,"time":144250,"type":0},{"id":1,"sLen":0,"time":144300,"type":0},{"id":0,"sLen":0,"time":144350,"type":0},{"id":2,"sLen":0,"time":144600,"type":0},{"id":3,"sLen":0,"time":144600,"type":0},{"id":2,"sLen":0,"time":145000,"type":0},{"id":0,"sLen":0,"time":145000,"type":0},{"id":1,"sLen":0,"time":145200,"type":0},{"id":3,"sLen":0,"time":145200,"type":0},{"id":2,"sLen":0,"time":145800,"type":0},{"id":1,"sLen":0,"time":145900,"type":0},{"id":3,"sLen":0,"time":146000,"type":0},{"id":0,"sLen":0,"time":146000,"type":0},{"id":1,"sLen":0,"time":146200,"type":0},{"id":2,"sLen":0,"time":146400,"type":0},{"id":3,"sLen":0,"time":146400,"type":0},{"id":0,"sLen":0,"time":146600,"type":0},{"id":1,"sLen":0,"time":146800,"type":0},{"id":2,"sLen":200,"time":146800,"type":0},{"id":0,"sLen":0,"time":147200,"type":0},{"id":1,"sLen":0,"time":147300,"type":0},{"id":0,"sLen":0,"time":147400,"type":0},{"id":3,"sLen":0,"time":147500,"type":0},{"id":2,"sLen":0,"time":147600,"type":0},{"id":1,"sLen":0,"time":147600,"type":0},{"id":0,"sLen":0,"time":147800,"type":0},{"id":3,"sLen":0,"time":148000,"type":0},{"id":1,"sLen":0,"time":148200,"type":0},{"id":0,"sLen":0,"time":148200,"type":0},{"id":0,"sLen":0,"time":148400,"type":0},{"id":2,"sLen":0,"time":148400,"type":0},{"id":1,"sLen":0,"time":148800,"type":0},{"id":3,"sLen":0,"time":148800,"type":0},{"id":2,"sLen":0,"time":149200,"type":0},{"id":3,"sLen":0,"time":149400,"type":0},{"id":1,"sLen":0,"time":149400,"type":0},{"id":0,"sLen":0,"time":149800,"type":0},{"id":0,"sLen":0,"time":149900,"type":0},{"id":2,"sLen":0,"time":150000,"type":0},{"id":1,"sLen":0,"time":150000,"type":0},{"id":1,"sLen":0,"time":150200,"type":0},{"id":3,"sLen":0,"time":150400,"type":1},{"id":2,"sLen":0,"time":150400,"type":1},{"id":0,"sLen":0,"time":150600,"type":0},{"id":1,"sLen":0,"time":150700,"type":0},{"id":0,"sLen":0,"time":150800,"type":0},{"id":2,"sLen":0,"time":150900,"type":0},{"id":3,"sLen":0,"time":151000,"type":0},{"id":1,"sLen":0,"time":151200,"type":0},{"id":2,"sLen":100,"time":151400,"type":0},{"id":3,"sLen":0,"time":151600,"type":0},{"id":0,"sLen":100,"time":151600,"type":0},{"id":2,"sLen":0,"time":152000,"type":0},{"id":2,"sLen":0,"time":152100,"type":0},{"id":1,"sLen":0,"time":152200,"type":0},{"id":3,"sLen":0,"time":152400,"type":0},{"id":0,"sLen":0,"time":152600,"type":0},{"id":0,"sLen":0,"time":152700,"type":0},{"id":1,"sLen":100,"time":152800,"type":0},{"id":2,"sLen":100,"time":153000,"type":0},{"id":0,"sLen":200,"time":153200,"type":0},{"id":3,"sLen":0,"time":153600,"type":0},{"id":1,"sLen":0,"time":153700,"type":0},{"id":3,"sLen":0,"time":153800,"type":0},{"id":2,"sLen":0,"time":153900,"type":0},{"id":0,"sLen":0,"time":154000,"type":0},{"id":1,"sLen":0,"time":154200,"type":0},{"id":3,"sLen":0,"time":154400,"type":0},{"id":2,"sLen":0,"time":154500,"type":0},{"id":1,"sLen":0,"time":154600,"type":0},{"id":0,"sLen":0,"time":154800,"type":0},{"id":3,"sLen":0,"time":154800,"type":0},{"id":1,"sLen":0,"time":155000,"type":0},{"id":2,"sLen":0,"time":155100,"type":0},{"id":3,"sLen":0,"time":155200,"type":0},{"id":1,"sLen":0,"time":155200,"type":0},{"id":0,"sLen":0,"time":155400,"type":0},{"id":0,"sLen":0,"time":155500,"type":0},{"id":2,"sLen":0,"time":155600,"type":0},{"id":1,"sLen":0,"time":155800,"type":0},{"id":3,"sLen":0,"time":156000,"type":0},{"id":3,"sLen":0,"time":156100,"type":0},{"id":1,"sLen":0,"time":156200,"type":0},{"id":2,"sLen":0,"time":156300,"type":0},{"id":0,"sLen":0,"time":156400,"type":0},{"id":3,"sLen":0,"time":156500,"type":0},{"id":2,"sLen":0,"time":156600,"type":0},{"id":1,"sLen":0,"time":156700,"type":0},{"id":3,"sLen":400,"time":156800,"type":1},{"id":0,"sLen":400,"time":156800,"type":1},{"id":0,"sLen":0,"time":163200,"type":0},{"id":3,"sLen":0,"time":163200,"type":0},{"id":1,"sLen":0,"time":163400,"type":0},{"id":2,"sLen":0,"time":163600,"type":0},{"id":3,"sLen":300,"time":163800,"type":0},{"id":0,"sLen":0,"time":164000,"type":0},{"id":1,"sLen":0,"time":164200,"type":0},{"id":2,"sLen":300,"time":164400,"type":0},{"id":0,"sLen":0,"time":164400,"type":0},{"id":3,"sLen":100,"time":164800,"type":0},{"id":1,"sLen":100,"time":165000,"type":0},{"id":0,"sLen":0,"time":165200,"type":0},{"id":2,"sLen":0,"time":165400,"type":0},{"id":1,"sLen":0,"time":165500,"type":0},{"id":3,"sLen":300,"time":165600,"type":0},{"id":0,"sLen":100,"time":166000,"type":0},{"id":2,"sLen":0,"time":166200,"type":0},{"id":1,"sLen":500,"time":166400,"type":0},{"id":2,"sLen":0,"time":167000,"type":0},{"id":3,"sLen":100,"time":167200,"type":0},{"id":2,"sLen":0,"time":167400,"type":0},{"id":1,"sLen":0,"time":167600,"type":0},{"id":0,"sLen":0,"time":167800,"type":0},{"id":1,"sLen":0,"time":168000,"type":0},{"id":3,"sLen":0,"time":168200,"type":0},{"id":1,"sLen":0,"time":168400,"type":0},{"id":2,"sLen":0,"time":168600,"type":0},{"id":0,"sLen":300,"time":168800,"type":0},{"id":3,"sLen":0,"time":169200,"type":0},{"id":1,"sLen":0,"time":169400,"type":0},{"id":2,"sLen":500,"time":169600,"type":0},{"id":0,"sLen":0,"time":170200,"type":0},{"id":1,"sLen":0,"time":170300,"type":0},{"id":3,"sLen":600,"time":170400,"type":0},{"id":2,"sLen":0,"time":170400,"type":0}],"characters":["BF_Goomba"],"type":1,"visible":true,"strumPos":[736,50]}],"codenameChart":true,"stage":"turmoilsweep","noteTypes":["No Animation"]}